[{"JatekosID":1,"CsapatID":1,"CsatlakozasDatum":"2021-03-01T00:00:00"},{"JatekosID":2,"CsapatID":1,"CsatlakozasDatum":"2021-04-12T00:00:00"},{"JatekosID":3,"CsapatID":1,"CsatlakozasDatum":"2021-05-20T00:00:00"},{"JatekosID":4,"CsapatID":1,"CsatlakozasDatum":"2021-06-10T00:00:00"},{"JatekosID":5,"CsapatID":1,"CsatlakozasDatum":"2021-07-05T00:00:00"},{"JatekosID":6,"CsapatID":1,"CsatlakozasDatum":"2021-08-22T00:00:00"},{"JatekosID":7,"CsapatID":2,"CsatlakozasDatum":"2021-03-15T00:00:00"},{"JatekosID":8,"CsapatID":2,"CsatlakozasDatum":"2021-04-02T00:00:00"},{"JatekosID":9,"CsapatID":2,"CsatlakozasDatum":"2021-04-30T00:00:00"},{"JatekosID":10,"CsapatID":2,"CsatlakozasDatum":"2021-05-18T00:00:00"},{"JatekosID":11,"CsapatID":2,"CsatlakozasDatum":"2021-06-07T00:00:00"},{"JatekosID":12,"CsapatID":2,"CsatlakozasDatum":"2021-07-25T00:00:00"},{"JatekosID":13,"CsapatID":3,"CsatlakozasDatum":"2021-03-10T00:00:00"},{"JatekosID":14,"CsapatID":3,"CsatlakozasDatum":"2021-03-29T00:00:00"},{"JatekosID":15,"CsapatID":3,"CsatlakozasDatum":"2021-04-17T00:00:00"},{"JatekosID":16,"CsapatID":3,"CsatlakozasDatum":"2021-05-09T00:00:00"},{"JatekosID":17,"CsapatID":3,"CsatlakozasDatum":"2021-06-14T00:00:00"},{"JatekosID":18,"CsapatID":3,"CsatlakozasDatum":"2021-07-01T00:00:00"},{"JatekosID":19,"CsapatID":4,"CsatlakozasDatum":"2021-02-20T00:00:00"},{"JatekosID":20,"CsapatID":4,"CsatlakozasDatum":"2021-03-11T00:00:00"},{"JatekosID":21,"CsapatID":4,"CsatlakozasDatum":"2021-04-01T00:00:00"},{"JatekosID":22,"CsapatID":4,"CsatlakozasDatum":"2021-04-25T00:00:00"},{"JatekosID":23,"CsapatID":4,"CsatlakozasDatum":"2021-05-16T00:00:00"},{"JatekosID":24,"CsapatID":4,"CsatlakozasDatum":"2021-06-03T00:00:00"},{"JatekosID":25,"CsapatID":5,"CsatlakozasDatum":"2021-03-08T00:00:00"},{"JatekosID":26,"CsapatID":5,"CsatlakozasDatum":"2021-03-28T00:00:00"},{"JatekosID":27,"CsapatID":5,"CsatlakozasDatum":"2021-04-13T00:00:00"},{"JatekosID":28,"CsapatID":5,"CsatlakozasDatum":"2021-05-02T00:00:00"},{"JatekosID":29,"CsapatID":5,"CsatlakozasDatum":"2021-05-27T00:00:00"},{"JatekosID":30,"CsapatID":5,"CsatlakozasDatum":"2021-06-12T00:00:00"},{"JatekosID":31,"CsapatID":6,"CsatlakozasDatum":"2021-03-19T00:00:00"},{"JatekosID":32,"CsapatID":6,"CsatlakozasDatum":"2021-04-08T00:00:00"},{"JatekosID":33,"CsapatID":6,"CsatlakozasDatum":"2021-04-22T00:00:00"},{"JatekosID":34,"CsapatID":6,"CsatlakozasDatum":"2021-05-13T00:00:00"},{"JatekosID":35,"CsapatID":6,"CsatlakozasDatum":"2021-06-05T00:00:00"},{"JatekosID":36,"CsapatID":6,"CsatlakozasDatum":"2021-06-27T00:00:00"},{"JatekosID":37,"CsapatID":7,"CsatlakozasDatum":"2021-03-04T00:00:00"},{"JatekosID":38,"CsapatID":7,"CsatlakozasDatum":"2021-03-23T00:00:00"},{"JatekosID":39,"CsapatID":7,"CsatlakozasDatum":"2021-04-14T00:00:00"},{"JatekosID":40,"CsapatID":7,"CsatlakozasDatum":"2021-05-07T00:00:00"},{"JatekosID":41,"CsapatID":7,"CsatlakozasDatum":"2021-05-25T00:00:00"},{"JatekosID":42,"CsapatID":7,"CsatlakozasDatum":"2021-06-18T00:00:00"},{"JatekosID":43,"CsapatID":8,"CsatlakozasDatum":"2021-02-25T00:00:00"},{"JatekosID":44,"CsapatID":8,"CsatlakozasDatum":"2021-03-19T00:00:00"},{"JatekosID":45,"CsapatID":8,"CsatlakozasDatum":"2021-04-03T00:00:00"},{"JatekosID":46,"CsapatID":8,"CsatlakozasDatum":"2021-04-26T00:00:00"},{"JatekosID":47,"CsapatID":8,"CsatlakozasDatum":"2021-05-20T00:00:00"},{"JatekosID":48,"CsapatID":8,"CsatlakozasDatum":"2021-06-08T00:00:00"},{"JatekosID":49,"CsapatID":9,"CsatlakozasDatum":"2021-03-15T00:00:00"},{"JatekosID":50,"CsapatID":9,"CsatlakozasDatum":"2021-03-31T00:00:00"},{"JatekosID":51,"CsapatID":9,"CsatlakozasDatum":"2021-04-20T00:00:00"},{"JatekosID":52,"CsapatID":9,"CsatlakozasDatum":"2021-05-10T00:00:00"},{"JatekosID":53,"CsapatID":9,"CsatlakozasDatum":"2021-05-29T00:00:00"},{"JatekosID":54,"CsapatID":9,"CsatlakozasDatum":"2021-06-15T00:00:00"},{"JatekosID":55,"CsapatID":10,"CsatlakozasDatum":"2021-03-06T00:00:00"},{"JatekosID":56,"CsapatID":10,"CsatlakozasDatum":"2021-03-27T00:00:00"},{"JatekosID":57,"CsapatID":10,"CsatlakozasDatum":"2021-04-16T00:00:00"},{"JatekosID":58,"CsapatID":10,"CsatlakozasDatum":"2021-05-06T00:00:00"},{"JatekosID":59,"CsapatID":10,"CsatlakozasDatum":"2021-05-24T00:00:00"},{"JatekosID":60,"CsapatID":10,"CsatlakozasDatum":"2021-06-11T00:00:00"}]